pylimn/__init__.py
pylimn/pylimn.py
pylimn-1.0.2.dist-info/DESCRIPTION.rst
pylimn-1.0.2.dist-info/METADATA
pylimn-1.0.2.dist-info/RECORD
pylimn-1.0.2.dist-info/WHEEL
pylimn-1.0.2.dist-info/metadata.json
pylimn-1.0.2.dist-info/top_level.txt
