Metadata-Version: 2.0
Name: pylimn
Version: 1.0.2
Summary: pylimn
Home-page: https://github.com/dfreelon/pylimn/
Author: Deen Freelon
Author-email: dfreelon@gmail.com
License: UNKNOWN
Download-URL: https://github.com/dfreelon/pylimn/
Keywords: natural language processing,nlp,named entity extraction,keyword in context,kwic,stemming
Platform: UNKNOWN
Requires-Dist: geostring
Requires-Dist: nltk
